{
    "H1": "Blood Donor online Calculator",
    "H2": "Click on the 'blood donor' button for getting results",
    "TITLE": "Blood donor - Calculate your blood donor eligibility now ",
    "META": "Evaluate your eligibility to donate blood with our calculator. Get your results in just a few minutes and learn how to become a blood donor.",
    "img": "/assets/images/hematology.png",
    "imgwidth": "35px",
    "imgheight": "35px",
    "height": "300px",
    "color": "#f0d50a",
    "keyword": "adjusted weight",
    "megaMenu": {
        "nav-link-name": "Tools",
        "dropdown": [
            {
                "categoryName": "Recommended Pages",
                "links": [
                    {
                        "name": "child-weight-calculator",
                        "url": "/child-percentile",
                        "hover": "blue"
                    },
                    {
                        "name": "birthweight percentile calculator",
                        "url": "/birthweight-percentile-calculator",
                        "hover": "blue"
                    }
                ]
            }
        ]
    },
    "TEXTUAL_CONTENT": [
        {
            "priority": 1,
            "logoUrl": "/assets/bulb.svg",
            "header": "",
            "content": ""
        },
        {
            "priority": 1,
            "logoUrl": "/assets/support.svg",
            "header": "",
            "content": ""
        },
        {
            "priority": 1,
            "logoUrl": "/assets/protect.svg",
            "header": "",
            "content": ""
        },
        {
            "priority": 1,
            "logoUrl": "/assets/easy.svg",
            "header": "",
            "content": ""
        },
        {
            "priority": 1,
            "logoUrl": "/assets/cloud.svg",
            "header": "",
            "content": ""
        }
    ],
    "HOW_TO_CONTENT": {
        "logoImageUrl": "/assets/pdf.svg",
        "heading": "",
        "steps": []
    },
    "FAQ": [],
    "jsfilepaths": [
        "/js/util.js",
        "/js/hematology-calculator/blood-donor-calculator.js"
    ],
    "calculatorData": {
        "calculatorWarning": "❗ This tool shouldn't be used as a substitute for clinical knowledge and/or consultation with a medical specialist. Always consult your doctor.",
    "calculatorRow": [
        {
            "labelName": "I want to...",
            "labelId": "I want to...__id",
            "inputId": "I want to..._input_Id",
            "dropDown": "donate",
            "dropDownId": "want_dd_Id",
            "dateTimePicker": false
        },
        {
            "labelName": "",
            "labelId": "__id",
            "inputId": "_input_Id",
            "dropDown": "blood",
            "dropDownId": "blood_dd_Id",
            "dateTimePicker": false
        },
        {
            "labelName": "My blood type",
            "labelId": "My blood type__id",
            "inputId": "My blood type_input_Id",
            "dropDown": "O+",
            "dropDownId": "type_dd_Id",
            "dateTimePicker": false
        }
    ],
    "ButtonValue": "Calculate",
    "ButtonId": "calculate_btn",
    "ButtonType": "submit",
    "resultDiv": "true",
    "resultDisplay": "none"
}
}