{
    "H1": "Diffuse Large B-cell Lymphoma Prognosis Calculator",
    "H2": "Click on the 'diffuse large lymphoma prognosis' button for results",
    "TITLE": "Accurately estimate your diffuse large b cell lymphoma prognosis risk",
    "META": "Use our diffuse large lymphoma calculator to quickly and easily determine your risk for diffuse large lymphoma. Get your results instantly.",
    "img": "/assets/images/hematology.png",
    "imgwidth": "35px",
    "imgheight": "35px",
    "height": "300px",
    "color": "#f0d50a",
    "keyword": "adjusted weight",
    "megaMenu": {
        "nav-link-name": "Tools",
        "dropdown": [
            {
                "categoryName": "Recommended Pages",
                "links": [
                    {
                        "name": "child-weight-calculator",
                        "url": "/child-percentile",
                        "hover": "blue"
                    },
                    {
                        "name": "birthweight percentile calculator",
                        "url": "/birthweight-percentile-calculator",
                        "hover": "blue"
                    }
                ]
            }
        ]
    },
    "TEXTUAL_CONTENT": [
        {
            "priority": 1,
            "logoUrl": "/assets/bulb.svg",
            "header": "",
            "content": ""
        },
        {
            "priority": 1,
            "logoUrl": "/assets/support.svg",
            "header": "",
            "content": ""
        },
        {
            "priority": 1,
            "logoUrl": "/assets/protect.svg",
            "header": "",
            "content": ""
        },
        {
            "priority": 1,
            "logoUrl": "/assets/easy.svg",
            "header": "",
            "content": ""
        },
        {
            "priority": 1,
            "logoUrl": "/assets/cloud.svg",
            "header": "",
            "content": ""
        }
    ],
    "HOW_TO_CONTENT": {
        "logoImageUrl": "/assets/pdf.svg",
        "heading": "",
        "steps": []
    },
    "FAQ": [],
    "jsfilepaths": [
        "/js/util.js",
        "/js/hematology-calculator/diffuse-large-lymphoma-prognosis.js"
    ],
    "calculatorData": {
        "calculatorWarning": "❗ This tool shouldn't be used as a substitute for clinical knowledge and/or consultation with a medical specialist. Always consult your doctor.",
        "calculatorRow": [
            {
                "labelName": "Age",
                "labelId": "Age__id",
                "inputId": "Age_input_Id",
                "dropDown": "<60 years",
                "dropDownId": "Age_dd_Id",
                "dateTimePicker": false
            },
            {
                "labelName": "Stage",
                "labelId": "Stage__id",
                "inputId": "Stage_input_Id",
                "dropDown": "I-II",
                "dropDownId": "Stage_dd_Id",
                "dateTimePicker": false
            },
            {
                "labelName": "Extranodal site",
                "labelId": "Extranodal site__id",
                "inputId": "Extranodal site_input_Id",
                "dropDown": "0 or 1",
                "dropDownId": "site_dd_Id",
                "dateTimePicker": false
            },
            {
                "labelName": "LDH",
                "labelId": "LDH__id",
                "inputId": "LDH_input_Id",
                "dropDown": "Normal (≤ 280 U/L)",
                "dropDownId": "LDH_dd_Id",
                "dateTimePicker": false
            },
            {
                "labelName": "ECOG/Zubrod performance status",
                "labelId": "ECOG/Zubrod performance status__id",
                "inputId": "ECOG/Zubrod performance status_input_Id",
                "dropDown": "0-1",
                "dropDownId": "status_dd_Id",
                "dateTimePicker": false
            }
        ],
        "ButtonValue": "Calculate",
        "ButtonId": "calculate_btn",
        "ButtonType": "submit",
        "resultDiv": "true",
        "resultDisplay": "none"
    }
}