{
    "H1": "weight percentile calculator online",
    "H2": "Enter your age, gender, and weight. Then click the \"Calculate weight\" button.",
    "TITLE": "child weight percentile - By using this tool to manage your body weight",
    "META": "Get started on a healthier lifestyle today by finding your adjusted body weight with our adjusted weight calculator",
    "img": "/assets/images/bscale.png",
    "height": "300px",
    "color": "#3287B2",
    "keyword": "adjusted weight",
    "megaMenu": {
        "nav-link-name": "Tools",
        "dropdown": [
            {
                "categoryName": "Recommended Pages",
                "links": [
                    {
                        "name": "baby-percentile ",
                        "url": "/baby-percentile",
                        "hover": "blue"
                    },
                    {
                        "name": "birthweight percentile",
                        "url": "/birthweight-percentile-calculator",
                        "hover": "blue"
                    }
                ]
            }
        ]
    },
    "TEXTUAL_CONTENT": [
        {
            "priority": 1,
            "logoUrl": "/assets/bulb.svg",
            "header": "",
            "content": ""
        },
        {
            "priority": 1,
            "logoUrl": "/assets/support.svg",
            "header": "",
            "content": ""
        },
        {
            "priority": 1,
            "logoUrl": "/assets/protect.svg",
            "header": "",
            "content": ""
        },
        {
            "priority": 1,
            "logoUrl": "/assets/easy.svg",
            "header": "",
            "content": ""
        },
        {
            "priority": 1,
            "logoUrl": "/assets/cloud.svg",
            "header": "",
            "content": ""
        }
    ],
    "HOW_TO_CONTENT": {
        "logoImageUrl": "/assets/pdf.svg",
        "heading": "",
        "steps": []
    },
    "FAQ": [],
    "jscdns": [
        "<script src=https://cdnjs.cloudflare.com/ajax/libs/mathjs/11.0.1/math.min.js></script>"
    ],
    "jsfilepaths": [
        "/js/util.js",
        "/js/Percentile-category/fetal-weight-percentile.js"
    ],
    "calculatorData": {
        "calculatorRow": [
            {
                "labelName": "Sex",
                "labelId": "Sex__id",
                "inputId": "Sex_input_Id",
                "dropDown": "Unknown",
                "dropDownId": "Sex_dd_Id",
                "dateTimePicker": false
            },
            {
                "labelName": "Gestational age",
                "labelId": "Gestational age__id",
                "inputBox": "text",
                "inputId": "Gage_input_Id",
                "dropDown": "wks",
                "dropDownId": "Gage_dd_Id",
                "dateTimePicker": false
            },
            {
                "labelName": "Abdominal Circumference",
                "labelId": "Abdominal Circumference__id",
                "inputBox": "text",
                "inputId": "aCircumference_input_Id",
                "dropDown": "mm",
                "dropDownId": "aCircumference_dd_Id",
                "dateTimePicker": false
            },
            {
                "labelName": "Head Circumference",
                "labelId": "Head Circumference__id",
                "inputBox": "text",
                "inputId": "hCircumference_input_Id",
                "dropDown": "mm",
                "dropDownId": "hCircumference_dd_Id",
                "dateTimePicker": false
            },
            {
                "labelName": "Biparietal Diameter",
                "labelId": "Biparietal Diameter__id",
                "inputBox": "text",
                "inputId": "Diameter_input_Id",
                "dropDown": "mm",
                "dropDownId": "Diameter_dd_Id",
                "dateTimePicker": false
            },
            {
                "labelName": "Femur Length",
                "labelId": "Femur Length__id",
                "inputBox": "text",
                "inputId": "Length_input_Id",
                "dropDown": "mm",
                "dropDownId": "Length_dd_Id",
                "dateTimePicker": false
            },
            {
                "labelName": "Estimated fetal weight",
                "labelId": "Estimated fetal weight__id",
                "inputBox": "text",
                "inputId": "weight_input_Id",
                "dropDown": "g",
                "dropDownId": "weight_dd_Id",
                "dateTimePicker": false
            }
        ],
        "ButtonValue": "Calculate",
        "ButtonId": "calculate_btn",
        "ButtonType": "submit",
        "resultDiv": "true",
        "resultDisplay": "none"
    }
}